{"UserName": "Sam Tarantino", "Picture": "110494-110495-1144571-1209681.jpg", "About": null, "TSModified": 1336683013, "UUID": "4d724ecc0563495614000036", "Username": "Sam Tarantino", "PlaylistID": 470, "UserID": 4, "LName": "", "AlbumFiles": ["1081303.jpg", "110495.jpg", "1144571.jpg", "1209681.jpg"], "UserPicture": "4.jpg", "FName": "Sam Tarantino", "TSAdded": "2007-11-15 00:00:00", "tooBig": false, "Songs": [{"SongID": "7608588", "EstimateDuration": "497", "Name": "Your Hand in Mine", "Popularity": "1407500448", "Year": "2003", "AlbumName": "The Earth Is Not a Cold Dead Place", "SongNameID": "186615", "AlbumID": "1144571", "ArtistID": "401444", "Flags": "0", "AvgRating": "0", "ArtistName": "Explosions in the Sky", "CoverArtFilename": "1144571.jpg", "IsLowBitrateAvailable": "1", "TrackNum": "5", "IsVerified": "1"}, {"SongID": "7608585", "EstimateDuration": "614", "Name": "The Only Moment We Were Alone", "Popularity": "1407500195", "Year": "2003", "AlbumName": "The Earth Is Not a Cold Dead Place", "SongNameID": "8131", "AlbumID": "1144571", "ArtistID": "401444", "Flags": "0", "AvgRating": "0", "ArtistName": "Explosions in the Sky", "CoverArtFilename": "1144571.jpg", "IsLowBitrateAvailable": "1", "TrackNum": "2", "IsVerified": "1"}, {"SongID": "7282085", "EstimateDuration": "530", "Name": "Memorial", "Popularity": "1407100008", "Year": "2003", "AlbumName": "The Earth Is Not a Cold Dead Place", "SongNameID": "8133", "AlbumID": "1144571", "ArtistID": "401444", "Flags": "0", "AvgRating": "0", "ArtistName": "Explosions in the Sky", "CoverArtFilename": "1144571.jpg", "IsLowBitrateAvailable": "1", "TrackNum": "4", "IsVerified": "0"}, {"SongID": "7608615", "EstimateDuration": "263", "Name": "Inside It All Feels the Same", "Popularity": "1407500001", "Year": "2004", "AlbumName": "Friday Night Lights Soundtrack", "SongNameID": "517233", "AlbumID": "110494", "ArtistID": "401444", "Flags": "0", "AvgRating": "0", "ArtistName": "Explosions in the Sky", "CoverArtFilename": "110494.jpg", "IsLowBitrateAvailable": "1", "TrackNum": "9", "IsVerified": "0"}, {"SongID": "12772864", "EstimateDuration": "411", "Name": "Lonely Train", "Popularity": "1404500004", "Year": "2004", "AlbumName": "Friday Night Lights Soundtrack", "SongNameID": "120760", "AlbumID": "110494", "ArtistID": "401444", "Flags": "0", "AvgRating": "0", "ArtistName": "Explosions in the Sky", "CoverArtFilename": "110494.jpg", "IsLowBitrateAvailable": "1", "TrackNum": "11", "IsVerified": "0"}, {"SongID": "7608611", "EstimateDuration": "161", "Name": "Our Last Days as Children", "Popularity": "1407500001", "Year": null, "AlbumName": "Unknown Album", "SongNameID": "517230", "AlbumID": "3015", "ArtistID": "401444", "Flags": "0", "AvgRating": "0", "ArtistName": "Explosions in the Sky", "CoverArtFilename": "3015.jpg", "IsLowBitrateAvailable": "1", "TrackNum": "3", "IsVerified": "0"}, {"SongID": "2125394", "EstimateDuration": "243", "Name": "Seagull", "Popularity": "1406100004", "Year": "2004", "AlbumName": "Friday Night Lights Soundtrack", "SongNameID": "31848", "AlbumID": "110494", "ArtistID": "401444", "Flags": "0", "AvgRating": "0", "ArtistName": "Explosions in the Sky", "CoverArtFilename": "110494.jpg", "IsLowBitrateAvailable": "1", "TrackNum": "12", "IsVerified": "0"}, {"SongID": "12772865", "EstimateDuration": "206", "Name": "Sonho Dourado", "Popularity": "1407500001", "Year": "2004", "AlbumName": "Friday Night Lights Soundtrack", "SongNameID": "246291", "AlbumID": "110495", "ArtistID": "28715", "Flags": "0", "AvgRating": "0", "ArtistName": "Daniel Lanois", "CoverArtFilename": "110495.jpg", "IsLowBitrateAvailable": "1", "TrackNum": "6", "IsVerified": "0"}, {"SongID": "7991817", "EstimateDuration": "340", "Name": "The Sky Above, The Field Below", "Popularity": "1407400001", "Year": "2004", "AlbumName": "Friday Night Lights Soundtrack", "SongNameID": "120762", "AlbumID": "110494", "ArtistID": "401444", "Flags": "0", "AvgRating": "0", "ArtistName": "Explosions in the Sky", "CoverArtFilename": "110494.jpg", "IsLowBitrateAvailable": "1", "TrackNum": "13", "IsVerified": "0"}, {"SongID": "14230628", "EstimateDuration": "246", "Name": "To West Texas", "Popularity": "1404500004", "Year": "2004", "AlbumName": "Friday Night Lights Soundtrack", "SongNameID": "8136", "AlbumID": "110494", "ArtistID": "401444", "Flags": "0", "AvgRating": "0", "ArtistName": "Explosions in the Sky", "CoverArtFilename": "110494.jpg", "IsLowBitrateAvailable": "1", "TrackNum": "7", "IsVerified": "0"}, {"SongID": "7992640", "EstimateDuration": "364", "Name": "A Poor Man's Memory", "Popularity": "1404400017", "Year": "2001", "AlbumName": "Those Who Tell the Truth Shall Die, Those Who Tell the Truth Shall Live Forever", "SongNameID": "80483", "AlbumID": "150280", "ArtistID": "401444", "Flags": "0", "AvgRating": "0", "ArtistName": "Explosions in the Sky", "CoverArtFilename": "150280.jpg", "IsLowBitrateAvailable": "1", "TrackNum": "1", "IsVerified": "0"}, {"SongID": "8690927", "EstimateDuration": "248", "Name": "Your Hand In Mine", "Popularity": "1407100006", "Year": "2004", "AlbumName": "Friday Night Lights", "SongNameID": "8225", "AlbumID": "347738", "ArtistID": "401444", "Flags": "0", "AvgRating": "0", "ArtistName": "Explosions in the Sky", "CoverArtFilename": "347738.png", "IsLowBitrateAvailable": "1", "TrackNum": "2", "IsVerified": "0"}], "Name": "Indie"}